MANIFEST.in
README.rst
setup.py
svglue/__init__.py
svglue.egg-info/PKG-INFO
svglue.egg-info/SOURCES.txt
svglue.egg-info/dependency_links.txt
svglue.egg-info/requires.txt
svglue.egg-info/top_level.txt