Metadata-Version: 1.0
Name: svglue
Version: 0.2dev
Summary: Create templates using Inkscape, then fill them in (and render them to PDF, if you like).
Home-page: http://github.com/mbr/svglue
Author: Marc Brinkmann
Author-email: git@marcbrinkmann.de
License: MIT
Platform: UNKNOWN
